<annotation>
	<folder>n13133613</folder>
	<filename>n13133613_5823</filename>
	<source>
		<database>ImageNet database</database>
	</source>
	<size>
		<width>500</width>
		<height>377</height>
		<depth>3</depth>
	</size>
	<segmented>0</segmented>
	<object>
		<name>n13133613</name>
		<pose>Unspecified</pose>
		<truncated>0</truncated>
		<difficult>0</difficult>
		<bndbox>
			<xmin>158</xmin>
			<ymin>238</ymin>
			<xmax>288</xmax>
			<ymax>312</ymax>
		</bndbox>
	</object>
</annotation>